ses_log_handler/__init__.py
ses_log_handler/handler.py
ses_log_handler-1.0.2.dist-info/WHEEL
ses_log_handler-1.0.2.dist-info/METADATA
ses_log_handler-1.0.2.dist-info/RECORD
